docs/source/conf.py
examples/contrast_script.py
examples/roc_script.py
pyklip/__init__.py
pyklip/covars.py
pyklip/empca.py
pyklip/fakes.py
pyklip/fitpsf.py
pyklip/fm.py
pyklip/klip.py
pyklip/nmf_imaging.py
pyklip/nmf_imaging_JAX.py
pyklip/parallelized.py
pyklip/rdi.py
pyklip/spectra_management.py
pyklip/zones.py
pyklip/fmlib/__init__.py
pyklip/fmlib/diskfm.py
pyklip/fmlib/extractSpec.py
pyklip/fmlib/fmpsf.py
pyklip/fmlib/matchedFilter.py
pyklip/fmlib/nofm.py
pyklip/instruments/CHARIS.py
pyklip/instruments/GPI.ini
pyklip/instruments/GPI.py
pyklip/instruments/Instrument.py
pyklip/instruments/JWST.py
pyklip/instruments/MagAO.ini
pyklip/instruments/MagAO.py
pyklip/instruments/NIRC2.ini
pyklip/instruments/NIRC2.py
pyklip/instruments/P1640.ini
pyklip/instruments/P1640.py
pyklip/instruments/SPHERE.py
pyklip/instruments/STIS.py
pyklip/instruments/__init__.py
pyklip/instruments/osiris.py
pyklip/instruments/GPI_profiles/gpi_offaxis_throughput_H.fits
pyklip/instruments/GPI_profiles/gpi_offaxis_throughput_J.fits
pyklip/instruments/GPI_profiles/gpi_offaxis_throughput_K1.fits
pyklip/instruments/GPI_profiles/gpi_offaxis_throughput_K2.fits
pyklip/instruments/GPI_profiles/gpi_offaxis_throughput_Y.fits
pyklip/instruments/P1640_support/P1640_cube_checker.py
pyklip/instruments/P1640_support/P1640_cube_checker_interactive.py
pyklip/instruments/P1640_support/P1640_spot_checker.py
pyklip/instruments/P1640_support/P1640contrast.py
pyklip/instruments/P1640_support/P1640cores.py
pyklip/instruments/P1640_support/P1640spots.py
pyklip/instruments/P1640_support/P1640utils.py
pyklip/instruments/P1640_support/WavelengthSol-KappaAndB0816.dat
pyklip/instruments/P1640_support/__init__.py
pyklip/instruments/utils/__init__.py
pyklip/instruments/utils/bkgd.py
pyklip/instruments/utils/global_centroid.py
pyklip/instruments/utils/nair.py
pyklip/instruments/utils/prntfFunction.py
pyklip/instruments/utils/radonCenter.py
pyklip/instruments/utils/wcsgen.py
pyklip/instruments/utils/xcorr.py
pyklip-2.9.dist-info/licenses/LICENSE
pyklip-2.9.dist-info/METADATA
pyklip-2.9.dist-info/WHEEL
pyklip-2.9.dist-info/top_level.txt
pyklip-2.9.dist-info/RECORD
