Metadata-Version: 2.4
Name: pyklip
Version: 2.9
Summary: pyKLIP: PSF Subtraction for Exoplanets and Disks
License-Expression: BSD-3-Clause
Keywords: KLIP,PSF Subtraction,Exoplanets,Astronomy
Classifier: Intended Audience :: Science/Research
Classifier: Topic :: Scientific/Engineering :: Astronomy
Classifier: Programming Language :: Python :: 3
License-File: LICENSE
Requires-Dist: numpy
Requires-Dist: scipy
Requires-Dist: astropy
Requires-Dist: matplotlib
Requires-Dist: emcee>3
Requires-Dist: corner
Requires-Dist: astroquery
Requires-Dist: tqdm
Dynamic: license-file
